extract_face/__init__.py
extract_face/data.py
extract_face/extract_face.py
extract_face/test.py
extract_face/data/haarcascade_frontalface_default.xml
extract_face-0.6.dist-info/LICENSE
extract_face-0.6.dist-info/METADATA
extract_face-0.6.dist-info/WHEEL
extract_face-0.6.dist-info/top_level.txt
extract_face-0.6.dist-info/RECORD
