Metadata-Version: 2.1
Name: extract-face
Version: 0.6
Summary: A Package which can extract all human faces from image
Home-page: UNKNOWN
Author: V2STech Solutions PVT. LTD.
Author-email: jayesht1996@gmail.com
License: UNKNOWN
Platform: UNKNOWN
Classifier: Programming Language :: Python :: 3
Classifier: License :: OSI Approved :: MIT License
Classifier: Operating System :: OS Independent
Requires-Dist: opencv-python
